simera/__init__.py
simera/activity.py
simera/cost.py
simera/presets.py
simera/ratesheet.py
simera/scenario.py
simera/scenario_item.py
simera/units.py
simera/utils.py
simera/zipcode.py
simera/config/__init__.py
simera/config/country.yaml
simera_inputs/config/generate_configs.py
simera-0.3.3.dist-info/METADATA
simera-0.3.3.dist-info/WHEEL
simera-0.3.3.dist-info/top_level.txt
simera-0.3.3.dist-info/RECORD
