Metadata-Version: 2.4
Name: simera
Version: 0.3.3
Summary: Supply Chain Simulation Tool
Author-email: "Artur. Blachnio" <blachnio.artur@gmail.com>
License: MIT
Requires-Python: >=3.6
Requires-Dist: pandas
Requires-Dist: openpyxl
Requires-Dist: pyxlsb
Requires-Dist: python-calamine
Requires-Dist: pyyaml
Requires-Dist: tqdm
